pyscaffoldext/pre_commit_ruff/__init__.py
pyscaffoldext/pre_commit_ruff/extension.py
pyscaffoldext/pre_commit_ruff/templates/__init__.py
pyscaffoldext/pre_commit_ruff/templates/pre-commit-ruff-config.template
pyscaffoldext/pre_commit_ruff/templates/pyproject_toml.template
pyscaffoldext/pre_commit_ruff/templates/setup_cfg.template
pyscaffoldext_pre_commit_ruff-1.0.2.dist-info/licenses/LICENSE.txt
pyscaffoldext_pre_commit_ruff-1.0.2.dist-info/METADATA
pyscaffoldext_pre_commit_ruff-1.0.2.dist-info/WHEEL
pyscaffoldext_pre_commit_ruff-1.0.2.dist-info/entry_points.txt
pyscaffoldext_pre_commit_ruff-1.0.2.dist-info/top_level.txt
pyscaffoldext_pre_commit_ruff-1.0.2.dist-info/RECORD
