Metadata-Version: 2.4
Name: pyscaffoldext-pre-commit-ruff
Version: 1.0.2
Summary: PyScaffold extension to use Ruff with pre-commit.
Home-page: https://github.com/jfishe/pyscaffoldext-pre-commit-ruff
Author: John D. Fisher
Author-email: jdfenw@gmail.com
License: MIT
Project-URL: Documentation, https://pyscaffoldext-pre-commit-ruff.readthedocs.io/
Project-URL: Source, https://github.com/jfishe/pyscaffoldext-pre-commit-ruff
Project-URL: Changelog, https://pyscaffoldext-pre-commit-ruff.readthedocs.io/en/latest/changelog.html
Project-URL: Tracker, https://github.com/jfishe/pyscaffoldext-pre-commit-ruff/issues
Platform: any
Classifier: Development Status :: 4 - Beta
Classifier: Programming Language :: Python
Requires-Python: >=3.8
License-File: LICENSE.txt
Requires-Dist: pyscaffold<5.0a0,>=4.6
Provides-Extra: testing
Requires-Dist: tox; extra == "testing"
Requires-Dist: pre-commit; extra == "testing"
Requires-Dist: setuptools_scm; extra == "testing"
Requires-Dist: virtualenv; extra == "testing"
Requires-Dist: configupdater; extra == "testing"
Requires-Dist: pytest; extra == "testing"
Requires-Dist: pytest-cov; extra == "testing"
Requires-Dist: pytest-xdist; extra == "testing"
Dynamic: license-file
